ginkgo_tools_redis/__init__.py
ginkgo_tools_redis/redis_advanced.py
ginkgo_tools_redis/redis_base.py
ginkgo_tools_redis/redis_manager.py
ginkgo_tools_redis/redis_ops.py
ginkgo_tools_redis-0.1.1.dist-info/METADATA
ginkgo_tools_redis-0.1.1.dist-info/WHEEL
ginkgo_tools_redis-0.1.1.dist-info/top_level.txt
ginkgo_tools_redis-0.1.1.dist-info/RECORD
