Metadata-Version: 2.4
Name: ginkgo-tools-redis
Version: 0.1.1
Summary: 对redis做了再封装，常规的redis操作和向量操作都做了简化，方便使用
Author-email: GINKGO <495466557@qq.com>
Keywords: tools,redis
Classifier: Development Status :: 3 - Alpha
Classifier: Intended Audience :: Developers
Classifier: License :: OSI Approved :: MIT License
Classifier: Programming Language :: Python :: 3
Classifier: Programming Language :: Python :: 3.6
Classifier: Programming Language :: Python :: 3.7
Classifier: Programming Language :: Python :: 3.8
Classifier: Programming Language :: Python :: 3.9
Classifier: Programming Language :: Python :: 3.10
Classifier: Programming Language :: Python :: 3.11
Requires-Python: >=3.11
Requires-Dist: ginkgo-tools>=0.1.4
Requires-Dist: redis[hiredis]==5.0.1
